digitalarztools/__init__.py
digitalarztools/adapters/__init__.py
digitalarztools/adapters/data_manager.py
digitalarztools/adapters/db.py
digitalarztools/adapters/manager-old.py
digitalarztools/adapters/manager.py
digitalarztools/adapters/model_utils.py
digitalarztools/distributions/GumbleDistribution.py
digitalarztools/distributions/__init__.py
digitalarztools/io/__init__.py
digitalarztools/io/file_io.py
digitalarztools/io/image_io.py
digitalarztools/io/url_io.py
digitalarztools/io/datasets/__init__.py
digitalarztools/io/datasets/rio_landsat.py
digitalarztools/io/datasets/rio_modis.py
digitalarztools/io/datasets/rio_probav_viirs.py
digitalarztools/io/map/__init__.py
digitalarztools/io/map/da_folium.py
digitalarztools/io/raster/__init__.py
digitalarztools/io/raster/band_process.py
digitalarztools/io/raster/cog_raster.py
digitalarztools/io/raster/dem_process.py
digitalarztools/io/raster/gdal_raster.py
digitalarztools/io/raster/gdal_raster_io.py
digitalarztools/io/raster/grib_reader.py
digitalarztools/io/raster/hdf_reader.py
digitalarztools/io/raster/indices.py
digitalarztools/io/raster/postgis_raster.py
digitalarztools/io/raster/rio_extraction.py
digitalarztools/io/raster/rio_process.py
digitalarztools/io/raster/rio_raster.py
digitalarztools/io/raster/rio_raster_20240707.py
digitalarztools/io/raster/rio_raster_collection.py
digitalarztools/io/raster/opencv/__init__.py
digitalarztools/io/raster/opencv/segmentation.py
digitalarztools/io/vector/__init__.py
digitalarztools/io/vector/gpd_vector.py
digitalarztools/modeling/__init__.py
digitalarztools/modeling/energy_blance_model.py
digitalarztools/modeling/heatwave_modeling.py
digitalarztools/modeling/hecras.py
digitalarztools/modeling/river_bed_profile.py
digitalarztools/modeling/surface_runoff.py
digitalarztools/pipelines/__init__.py
digitalarztools/pipelines/alos_palser.py
digitalarztools/pipelines/fao_livestock.py
digitalarztools/pipelines/grace.py
digitalarztools/pipelines/openstreetmap.py
digitalarztools-0.2.5.dist-info/METADATA
digitalarztools-0.2.5.dist-info/WHEEL
digitalarztools-0.2.5.dist-info/top_level.txt
digitalarztools-0.2.5.dist-info/RECORD
