Metadata-Version: 2.1
Name: digitalarztools
Version: 0.2.5
Summary: DigitalArz Tools for applications
Author: Ather Ashraf
Author-email: atherashraf@gmail.com
Keywords: raster,vector,digitalarz
Classifier: Development Status :: 1 - Planning
Classifier: Intended Audience :: Education
Classifier: Programming Language :: Python :: 3
Classifier: Operating System :: MacOS :: MacOS X
Classifier: Operating System :: Microsoft :: Windows
Requires-Python: >=3
Requires-Dist: affine==2.4.0
Requires-Dist: alphashape==1.3.1
Requires-Dist: annotated-types==0.7.0
Requires-Dist: anyio==4.6.2.post1
Requires-Dist: asf_search==8.0.1
Requires-Dist: attrs==24.2.0
Requires-Dist: beautifulsoup4==4.12.3
Requires-Dist: bleach==6.2.0
Requires-Dist: boto3==1.35.76
Requires-Dist: botocore
Requires-Dist: branca==0.8.0
Requires-Dist: cachetools==5.5.0
Requires-Dist: cattrs==24.1.2
Requires-Dist: cdsapi==0.7.5
Requires-Dist: certifi==2024.8.30
Requires-Dist: cffi==1.17.1
Requires-Dist: cfgrib==0.9.14.1
Requires-Dist: cftime==1.6.4.post1
Requires-Dist: charset-normalizer==3.4.0
Requires-Dist: click==8.1.7
Requires-Dist: click-log==0.4.0
Requires-Dist: click-plugins==1.1.1
Requires-Dist: cligj==0.7.2
Requires-Dist: color-operations==0.1.6
Requires-Dist: colorama
Requires-Dist: cryptography==44.0.0
Requires-Dist: datapi==0.1.1
Requires-Dist: dateparser==1.2.0
Requires-Dist: docutils==0.21.2
Requires-Dist: dotenv==0.9.9
Requires-Dist: earthengine-api==1.4.2
Requires-Dist: eccodes==2.39.0
Requires-Dist: et_xmlfile==2.0.0
Requires-Dist: findlibs==0.0.5
Requires-Dist: fiona==1.10.1
Requires-Dist: flatbuffers==24.3.25
Requires-Dist: folium
Requires-Dist: GDAL
Requires-Dist: GeoAlchemy2==0.17.1
Requires-Dist: geopandas==1.0.1
Requires-Dist: geojson==3.2.0
Requires-Dist: google-api-core==2.23.0
Requires-Dist: google-api-python-client==2.173.0
Requires-Dist: google-auth==2.36.0
Requires-Dist: google-auth-httplib2==0.2.0
Requires-Dist: google-cloud-core==2.4.1
Requires-Dist: google-cloud-storage==2.19.0
Requires-Dist: google-crc32c==1.6.0
Requires-Dist: google-resumable-media==2.7.2
Requires-Dist: googleapis-common-protos==1.66.0
Requires-Dist: greenlet==3.1.1
Requires-Dist: h11==0.14.0
Requires-Dist: httpcore==1.0.7
Requires-Dist: httplib2==0.22.0
Requires-Dist: httpx==0.28.0
Requires-Dist: idna==3.10
Requires-Dist: imageio==2.36.1
Requires-Dist: importlib_metadata==8.5.0
Requires-Dist: jaraco.classes==3.4.0
Requires-Dist: jaraco.context==6.0.1
Requires-Dist: jaraco.functools==4.1.0
Requires-Dist: Jinja2==3.1.4
Requires-Dist: jmespath==1.0.1
Requires-Dist: joblib==1.4.2
Requires-Dist: keyring==25.5.0
Requires-Dist: lazy_loader==0.4
Requires-Dist: lxml==5.3.0
Requires-Dist: markdown-it-py==3.0.0
Requires-Dist: MarkupSafe==3.0.2
Requires-Dist: matplotlib
Requires-Dist: mdurl==0.1.2
Requires-Dist: mercantile==1.2.1
Requires-Dist: more-itertools==10.5.0
Requires-Dist: morecantile==6.1.0
Requires-Dist: multiurl==0.3.3
Requires-Dist: networkx
Requires-Dist: nh3==0.2.19
Requires-Dist: numexpr==2.10.2
Requires-Dist: numpy
Requires-Dist: openmeteo_requests==1.3.0
Requires-Dist: openmeteo_sdk==1.18.0
Requires-Dist: openpyxl==3.1.5
Requires-Dist: packaging==24.2
Requires-Dist: pandas==2.2.3
Requires-Dist: pillow==11.0.0
Requires-Dist: pipdeptree==2.24.0
Requires-Dist: pkginfo==1.12.0
Requires-Dist: platformdirs==4.3.6
Requires-Dist: proto-plus==1.25.0
Requires-Dist: protobuf==5.29.1
Requires-Dist: pyasn1==0.6.1
Requires-Dist: pyasn1_modules==0.4.1
Requires-Dist: pycparser==2.22
Requires-Dist: pydantic==2.10.3
Requires-Dist: pydantic_core==2.27.1
Requires-Dist: Pygments==2.18.0
Requires-Dist: pyogrio==0.10.0
Requires-Dist: pyparsing==3.2.0
Requires-Dist: pyproj
Requires-Dist: pystac
Requires-Dist: python-dateutil==2.9.0.post0
Requires-Dist: python-dotenv==1.0.1
Requires-Dist: pytz==2024.2
Requires-Dist: rasterio==1.4.3
Requires-Dist: readme_renderer==44.0
Requires-Dist: regex==2024.11.6
Requires-Dist: requests==2.32.3
Requires-Dist: requests-cache==1.2.1
Requires-Dist: requests-toolbelt==1.0.0
Requires-Dist: retry-requests==2.0.0
Requires-Dist: rfc3986==2.0.0
Requires-Dist: rich==13.9.4
Requires-Dist: rio-cogeo==5.4.0
Requires-Dist: rio-tiler==7.2.2
Requires-Dist: rsa==4.9
Requires-Dist: Rtree==1.3.0
Requires-Dist: s3transfer==0.10.4
Requires-Dist: scikit-image==0.24.0
Requires-Dist: scikit-learn==1.5.2
Requires-Dist: scipy
Requires-Dist: setuptools==75.6.0
Requires-Dist: shapely==2.0.6
Requires-Dist: six==1.17.0
Requires-Dist: sniffio==1.3.1
Requires-Dist: soupsieve==2.6
Requires-Dist: SQLAlchemy==2.0.36
Requires-Dist: tenacity==8.2.2
Requires-Dist: threadpoolctl==3.5.0
Requires-Dist: tifffile
Requires-Dist: tqdm==4.67.1
Requires-Dist: trimesh==4.5.3
Requires-Dist: twine==6.0.1
Requires-Dist: typing_extensions==4.12.2
Requires-Dist: tzdata==2024.2
Requires-Dist: tzlocal==5.2
Requires-Dist: uritemplate==4.1.1
Requires-Dist: url-normalize==1.4.3
Requires-Dist: urllib3
Requires-Dist: webencodings==0.5.1
Requires-Dist: xarray
Requires-Dist: xyzservices==2024.9.0
Requires-Dist: zipp==3.21.0
